hanzo_async/__init__.py
hanzo_async/files.py
hanzo_async/paths.py
hanzo_async/process.py
hanzo_async-0.1.1.dist-info/METADATA
hanzo_async-0.1.1.dist-info/WHEEL
hanzo_async-0.1.1.dist-info/top_level.txt
hanzo_async-0.1.1.dist-info/RECORD
