Metadata-Version: 2.4
Name: hanzo-async
Version: 0.1.1
Summary: Unified async I/O for Hanzo AI - high-performance with uvloop fallback
Author-email: Hanzo Industries Inc <dev@hanzo.ai>
License: MIT
Project-URL: Homepage, https://github.com/hanzoai/python-sdk
Keywords: hanzo,async,uvloop,aiofiles,high-performance
Classifier: Programming Language :: Python :: 3
Classifier: License :: OSI Approved :: MIT License
Classifier: Operating System :: OS Independent
Requires-Python: >=3.12
Requires-Dist: aiofiles>=23.2.1
Provides-Extra: uvloop
Requires-Dist: uvloop>=0.21.0; sys_platform != "win32" and extra == "uvloop"
Provides-Extra: full
Requires-Dist: uvloop>=0.21.0; sys_platform != "win32" and extra == "full"
Provides-Extra: dev
Requires-Dist: pytest>=7.0.0; extra == "dev"
Requires-Dist: pytest-asyncio>=0.21.0; extra == "dev"
Requires-Dist: ruff>=0.14.0; extra == "dev"
